ivy/__init__.py
ivy/ivy.py
ivy/std_api.py
ivy_python-3.3.data/scripts/ivyprobe.py
ivy_python-3.3.dist-info/LICENSE
ivy_python-3.3.dist-info/METADATA
ivy_python-3.3.dist-info/WHEEL
ivy_python-3.3.dist-info/top_level.txt
ivy_python-3.3.dist-info/RECORD
