Metadata-Version: 2.1
Name: ivy-python
Version: 3.3
Summary: Ivy: a lightweight software bus
Home-page: https://www.eei.cena.fr/products/ivy/
Author: Sébastien Bigaret
Author-email: sebastien.bigaret@telecom-bretagne.eu
Maintainer: Sebastien Bigaret
Maintainer-email: sebastien.bigaret@telecom-bretagne.eu
License: BSD License
Project-URL: Documentation, https://ivy-python.readthedocs.io/
Project-URL: Bug Tracker, https://gitlab.com/ivybus/ivy-python/issues
Project-URL: Source Code, https://gitlab.com/ivybus/ivy-python/
Platform: UNKNOWN
Classifier: Development Status :: 6 - Mature
Classifier: Intended Audience :: Developers
Classifier: License :: OSI Approved :: BSD License
Classifier: Operating System :: OS Independent
Classifier: Programming Language :: Python
Classifier: Programming Language :: Python :: 2.7
Classifier: Programming Language :: Python :: 3
Classifier: Natural Language :: English
Classifier: Natural Language :: French
Classifier: Topic :: Software Development :: Libraries :: Python Modules
